pyThorlabsPM100x/__init__.py
pyThorlabsPM100x/config.json
pyThorlabsPM100x/driver.py
pyThorlabsPM100x/driver_virtual.py
pyThorlabsPM100x/main.py
pyThorlabsPM100x/plots.py
pyThorlabsPM100x/graphics/pause.png
pyThorlabsPM100x/graphics/play.png
pyThorlabsPM100x/graphics/refresh.png
pyThorlabsPM100x/graphics/stop.png
pyThorlabsPM100x-0.27.dist-info/METADATA
pyThorlabsPM100x-0.27.dist-info/WHEEL
pyThorlabsPM100x-0.27.dist-info/entry_points.txt
pyThorlabsPM100x-0.27.dist-info/top_level.txt
pyThorlabsPM100x-0.27.dist-info/RECORD
