Metadata-Version: 2.1
Name: pyThorlabsPM100x
Version: 0.27
Summary: A python library/GUI to access and control the PM100x consoles of Thorlabs.
Home-page: https://github.com/MicheleCotrufo/
Author: Michele Cotrufo
Author-email: michele.cotrufo@gmail.com
License: MIT
Platform: UNKNOWN
Requires-Dist: pyvisa
